pytaboola/__init__.py
pytaboola/client.py
pytaboola/errors.py
pytaboola/services/__init__.py
pytaboola/services/base.py
pytaboola/services/report.py
pytaboola/services/resource.py
pytaboola/services/service.py
pytaboola/utils/__init__.py
pytaboola-0.1.2.dist-info/METADATA
pytaboola-0.1.2.dist-info/RECORD
pytaboola-0.1.2.dist-info/WHEEL
pytaboola-0.1.2.dist-info/top_level.txt
