Metadata-Version: 2.1
Name: pytaboola
Version: 0.1.2
Summary: Python client for Taboola API
Home-page: https://github.com/dolead/pytaboola
Author: Antoine Francais
Author-email: antoine.francais@gmail.com
Maintainer: Dolead
Maintainer-email: it@dolead.com
License: MIT
Keywords: taboola api
Platform: UNKNOWN
Classifier: Programming Language :: Python :: 3
Classifier: Topic :: Software Development :: Libraries :: Python Modules
Classifier: License :: OSI Approved :: MIT License
Requires-Dist: requests
Requires-Dist: python-dateutil
